justdb/__init__.py
justdb/__main__.py
justdb/client.py
justdb/server.py
justdb-0.0.14.dist-info/DESCRIPTION.rst
justdb-0.0.14.dist-info/METADATA
justdb-0.0.14.dist-info/RECORD
justdb-0.0.14.dist-info/WHEEL
justdb-0.0.14.dist-info/entry_points.txt
justdb-0.0.14.dist-info/metadata.json
justdb-0.0.14.dist-info/top_level.txt
